{
  "document_id": "fs:d2b2234e1c1dbb75",
  "pages": 3,
  "contract_version": "1.0.0+32d6b8ce1ec8",
  "feature_version": "v1",
  "decoder_version": "v1",
  "model_version": "unscored-baseline",
  "calibration_version": "none",
  "fields": {
    "InvoiceNumber": {
      "value": "8529.00",
      "confidence": 0.0,
      "status": "PREDICTED",
      "provenance": {
        "page": 0,
        "bbox": [
          0.7515294117647059,
          0.0,
          0.7938398692810458,
          0.0
        ],
        "token_span": [
          "218",
          "206",
          "187",
          "181",
          "169",
          "201",
          "17",
          "219"
        ]
      },
      "raw_text": "Do Make Nov 8529 check $ to not"
    },
    "InvoiceDate": {
      "value": "8529.00",
      "confidence": 0.0,
      "status": "PREDICTED",
      "provenance": {
        "page": 0,
        "bbox": [
          0.7515294117647059,
          0.0,
          0.8036601310457516,
          0.0
        ],
        "token_span": [
          "206",
          "187",
          "181",
          "169",
          "201",
          "17",
          "219",
          "18"
        ]
      },
      "raw_text": "Make Nov 8529 check $ to not Nov"
    },
    "DueDate": {
      "value": "234032023.00",
      "confidence": 0.0,
      "status": "PREDICTED",
      "provenance": {
        "page": 0,
        "bbox": [
          0.8035294117647058,
          0.0,
          0.8592467320261437,
          0.0
        ],
        "token_span": [
          "171",
          "60",
          "19",
          "183",
          "189",
          "103",
          "221",
          "61"
        ]
      },
      "raw_text": "money of 23, 403 2023 bill. cash your"
    },
    "IssueDate": {
      "value": "234032023.00",
      "confidence": 0.0,
      "status": "PREDICTED",
      "provenance": {
        "page": 0,
        "bbox": [
          0.7985686274019608,
          0.0,
          0.8592467320261437,
          0.0
        ],
        "token_span": [
          "112",
          "171",
          "60",
          "19",
          "183",
          "189",
          "103",
          "221"
        ]
      },
      "raw_text": "balance money of 23, 403 2023 bill. cash"
    },
    "TotalAmount": {
      "value": "11234032023.00",
      "confidence": 0.0,
      "status": "PREDICTED",
      "provenance": {
        "page": 0,
        "bbox": [
          0.7981895424836601,
          0.0,
          0.8592467320261437,
          0.0
        ],
        "token_span": [
          "182",
          "112",
          "171",
          "60",
          "19",
          "183",
          "189",
          "103"
        ]
      },
      "raw_text": "11 balance money of 23, 403 2023 bill."
    },
    "Subtotal": {
      "value": null,
      "confidence": 0.0,
      "status": "ABSTAIN",
      "provenance": {
        "page": 0,
        "bbox": [
          0.39458823562091505,
          0.0,
          0.452352943872549,
          0.0
        ],
        "token_span": [
          "7",
          "0",
          "129",
          "85",
          "120",
          "74",
          "106",
          "126"
        ]
      },
      "raw_text": "8529 Account $194.90 -$194.90 $194.90 $194.90 $0.00 $0.00"
    },
    "TaxAmount": {
      "value": null,
      "confidence": 0.0,
      "status": "ABSTAIN",
      "provenance": {
        "page": 0,
        "bbox": [
          0.39458823562091505,
          0.0,
          0.452352943872549,
          0.0
        ],
        "token_span": [
          "0",
          "129",
          "85",
          "120",
          "74",
          "106",
          "126",
          "8"
        ]
      },
      "raw_text": "Account $194.90 -$194.90 $194.90 $194.90 $0.00 $0.00 11"
    },
    "Discount": {
      "value": "242023.00",
      "confidence": 0.0,
      "status": "PREDICTED",
      "provenance": {
        "page": 0,
        "bbox": [
          0.7035163401960784,
          0.0,
          0.7608366016339869,
          0.0
        ],
        "token_span": [
          "15",
          "99",
          "167",
          "90",
          "168",
          "16",
          "100",
          "5"
        ]
      },
      "raw_text": "24, up on or your 2023 on From"
    },
    "Currency": {
      "value": "10.00",
      "confidence": 0.0,
      "status": "PREDICTED",
      "provenance": {
        "page": 0,
        "bbox": [
          0.20776470588235296,
          0.0,
          0.26119607843137266,
          0.0
        ],
        "token_span": [
          "154",
          "45",
          "133",
          "155",
          "177",
          "82",
          "46",
          "156"
        ]
      },
      "raw_text": "of RD, 10, this with you STE bill"
    },
    "RemittanceAddress": {
      "value": "10.11",
      "confidence": 0.0,
      "status": "PREDICTED",
      "provenance": {
        "page": 0,
        "bbox": [
          0.7828333332843138,
          0.0,
          0.8423627450490195,
          0.0
        ],
        "token_span": [
          "69",
          "102",
          "207",
          "170",
          "188",
          "92",
          "220",
          "182"
        ]
      },
      "raw_text": "charges next checks or 10, activity send 11"
    },
    "BillToAddress": {
      "value": null,
      "confidence": 0.0,
      "status": "ABSTAIN",
      "provenance": {
        "page": 0,
        "bbox": [
          0.3925735258169935,
          0.0,
          0.4523529434150326,
          0.0
        ],
        "token_span": [
          "145",
          "7",
          "0",
          "129",
          "85",
          "120",
          "74",
          "106"
        ]
      },
      "raw_text": "other 8529 Account $194.90 -$194.90 $194.90 $194.90 $0.00"
    },
    "ShipToAddress": {
      "value": "11234032023.00",
      "confidence": 0.0,
      "status": "PREDICTED",
      "provenance": {
        "page": 0,
        "bbox": [
          0.793514705882353,
          0.0,
          0.8592467320261437,
          0.0
        ],
        "token_span": [
          "220",
          "182",
          "112",
          "171",
          "60",
          "19",
          "183",
          "189"
        ]
      },
      "raw_text": "send 11 balance money of 23, 403 2023"
    },
    "VendorName": {
      "value": null,
      "confidence": 0.0,
      "status": "ABSTAIN",
      "provenance": {
        "page": 0,
        "bbox": [
          0.39155555555555555,
          0.0,
          0.4523529434150326,
          0.0
        ],
        "token_span": [
          "50",
          "145",
          "7",
          "0",
          "129",
          "85",
          "120",
          "74"
        ]
      },
      "raw_text": "MI, other 8529 Account $194.90 -$194.90 $194.90 $194.90"
    },
    "VendorAddress": {
      "value": "203.00",
      "confidence": 0.0,
      "status": "PREDICTED",
      "provenance": {
        "page": 0,
        "bbox": [
          0.5808529411764706,
          0.0,
          0.6460686274019608,
          0.0
        ],
        "token_span": [
          "186",
          "164",
          "108",
          "12",
          "76",
          "231",
          "65",
          "227"
        ]
      },
      "raw_text": "due your your 20, 3. BOX detailed payment"
    },
    "CustomerName": {
      "value": "242023.00",
      "confidence": 0.0,
      "status": "PREDICTED",
      "provenance": {
        "page": 0,
        "bbox": [
          0.696759803872549,
          0.0,
          0.7585490199346405,
          0.0
        ],
        "token_span": [
          "58",
          "15",
          "99",
          "167",
          "90",
          "168",
          "16",
          "100"
        ]
      },
      "raw_text": "quick 24, up on or your 2023 on"
    },
    "CustomerAccount": {
      "value": "234032023.20",
      "confidence": 0.0,
      "status": "PREDICTED",
      "provenance": {
        "page": 0,
        "bbox": [
          0.8068235297385621,
          0.0,
          0.8742132352941177,
          0.0
        ],
        "token_span": [
          "19",
          "183",
          "189",
          "103",
          "221",
          "61",
          "208",
          "20"
        ]
      },
      "raw_text": "23, 403 2023 bill. cash your payable 2023"
    },
    "PurchaseOrder": {
      "value": null,
      "confidence": 0.0,
      "status": "ABSTAIN",
      "provenance": {
        "page": 0,
        "bbox": [
          0.38921078431372547,
          0.0,
          0.4523529434150326,
          0.0
        ],
        "token_span": [
          "161",
          "50",
          "145",
          "7",
          "0",
          "129",
          "85",
          "120"
        ]
      },
      "raw_text": "payment MI, other 8529 Account $194.90 -$194.90 $194.90"
    },
    "InvoiceReference": {
      "value": "10.00",
      "confidence": 0.0,
      "status": "PREDICTED",
      "provenance": {
        "page": 0,
        "bbox": [
          0.7785490199346404,
          0.0,
          0.8423627450490195,
          0.0
        ],
        "token_span": [
          "18",
          "69",
          "102",
          "207",
          "170",
          "188",
          "92",
          "220"
        ]
      },
      "raw_text": "Nov charges next checks or 10, activity send"
    },
    "PaymentTerms": {
      "value": "234032023.00",
      "confidence": 0.0,
      "status": "PREDICTED",
      "provenance": {
        "page": 0,
        "bbox": [
          0.8066862744607843,
          0.0,
          0.8742132352941177,
          0.0
        ],
        "token_span": [
          "60",
          "19",
          "183",
          "189",
          "103",
          "221",
          "61",
          "208"
        ]
      },
      "raw_text": "of 23, 403 2023 bill. cash your payable"
    },
    "BankAccount": {
      "value": "41112.00",
      "confidence": 0.0,
      "status": "PREDICTED",
      "provenance": {
        "page": 0,
        "bbox": [
          0.05352941176470588,
          0.0,
          0.11691503267973857,
          0.0
        ],
        "token_span": [
          "121",
          "104",
          "40",
          "127",
          "115",
          "190",
          "204",
          "202"
        ]
      },
      "raw_text": "Taxes, Balance For New Regular 41112 ATTN SPARROW"
    },
    "RoutingNumber": {
      "value": "1123403.00",
      "confidence": 0.0,
      "status": "PREDICTED",
      "provenance": {
        "page": 0,
        "bbox": [
          0.7904215685784314,
          0.0,
          0.8538186274019606,
          0.0
        ],
        "token_span": [
          "92",
          "220",
          "182",
          "112",
          "171",
          "60",
          "19",
          "183"
        ]
      },
      "raw_text": "activity send 11 balance money of 23, 403"
    },
    "SWIFTCode": {
      "value": "203.00",
      "confidence": 0.0,
      "status": "PREDICTED",
      "provenance": {
        "page": 0,
        "bbox": [
          0.5784362744607843,
          0.0,
          0.6460686274019608,
          0.0
        ],
        "token_span": [
          "54",
          "186",
          "164",
          "108",
          "12",
          "76",
          "231",
          "65"
        ]
      },
      "raw_text": "page due your your 20, 3. BOX detailed"
    },
    "LineItemDescription": {
      "value": "101123.00",
      "confidence": 0.0,
      "status": "PREDICTED",
      "provenance": {
        "page": 0,
        "bbox": [
          0.7895980392156864,
          0.0,
          0.8538186274019606,
          0.0
        ],
        "token_span": [
          "188",
          "92",
          "220",
          "182",
          "112",
          "171",
          "60",
          "19"
        ]
      },
      "raw_text": "10, activity send 11 balance money of 23,"
    },
    "LineItemQuantity": {
      "value": "10.11",
      "confidence": 0.0,
      "status": "PREDICTED",
      "provenance": {
        "page": 0,
        "bbox": [
          0.7890318627450981,
          0.0,
          0.8538186274019606,
          0.0
        ],
        "token_span": [
          "170",
          "188",
          "92",
          "220",
          "182",
          "112",
          "171",
          "60"
        ]
      },
      "raw_text": "or 10, activity send 11 balance money of"
    },
    "LineItemUnitPrice": {
      "value": "0.20",
      "confidence": 0.0,
      "status": "PREDICTED",
      "provenance": {
        "page": 0,
        "bbox": [
          0.8176421568137255,
          0.0,
          0.8861568626960785,
          0.0
        ],
        "token_span": [
          "103",
          "221",
          "61",
          "208",
          "20",
          "70",
          "172",
          "93"
        ]
      },
      "raw_text": "bill. cash your payable 2023 begins order after"
    },
    "LineItemTotal": {
      "value": "2023.20",
      "confidence": 0.0,
      "status": "PREDICTED",
      "provenance": {
        "page": 0,
        "bbox": [
          0.8174754901960785,
          0.0,
          0.8861568626960785,
          0.0
        ],
        "token_span": [
          "189",
          "103",
          "221",
          "61",
          "208",
          "20",
          "70",
          "172"
        ]
      },
      "raw_text": "2023 bill. cash your payable 2023 begins order"
    },
    "Notes": {
      "value": "203.00",
      "confidence": 0.0,
      "status": "PREDICTED",
      "provenance": {
        "page": 0,
        "bbox": [
          0.5780833332843137,
          0.0,
          0.6471127450490196,
          0.0
        ],
        "token_span": [
          "88",
          "54",
          "186",
          "164",
          "108",
          "12",
          "76",
          "231"
        ]
      },
      "raw_text": "payments page due your your 20, 3. BOX"
    },
    "TaxID": {
      "value": "4032023.20",
      "confidence": 0.0,
      "status": "PREDICTED",
      "provenance": {
        "page": 0,
        "bbox": [
          0.8164150326797386,
          0.0,
          0.8861568626960785,
          0.0
        ],
        "token_span": [
          "183",
          "189",
          "103",
          "221",
          "61",
          "208",
          "20",
          "70"
        ]
      },
      "raw_text": "403 2023 bill. cash your payable 2023 begins"
    },
    "ContactName": {
      "value": "20203.00",
      "confidence": 0.0,
      "status": "PREDICTED",
      "provenance": {
        "page": 0,
        "bbox": [
          0.577009803872549,
          0.0,
          0.6471127450490196,
          0.0
        ],
        "token_span": [
          "95",
          "88",
          "54",
          "186",
          "164",
          "108",
          "12",
          "76"
        ]
      },
      "raw_text": "20, payments page due your your 20, 3."
    },
    "ContactEmail": {
      "value": "2020.00",
      "confidence": 0.0,
      "status": "PREDICTED",
      "provenance": {
        "page": 0,
        "bbox": [
          0.5763382352941177,
          0.0,
          0.6471127450490196,
          0.0
        ],
        "token_span": [
          "180",
          "95",
          "88",
          "54",
          "186",
          "164",
          "108",
          "12"
        ]
      },
      "raw_text": "number 20, payments page due your your 20,"
    },
    "ContactPhone": {
      "value": "20.00",
      "confidence": 0.0,
      "status": "PREDICTED",
      "provenance": {
        "page": 0,
        "bbox": [
          0.5761568626960784,
          0.0,
          0.6471127450490196,
          0.0
        ],
        "token_span": [
          "64",
          "180",
          "95",
          "88",
          "54",
          "186",
          "164",
          "108"
        ]
      },
      "raw_text": "A number 20, payments page due your your"
    }
  },
  "line_items": [],
  "extensions": {},
  "experimental": {}
}